darl/__init__.py
darl/cache.py
darl/call_key.py
darl/collect.py
darl/constants.py
darl/dep_proxy.py
darl/engine.py
darl/error_handling.py
darl/graph.py
darl/graph_caching.py
darl/helpers.py
darl/mock_engine.py
darl/provider.py
darl/service_caller.py
darl/service_mapping.py
darl/special_providers.py
darl/trace.py
darl/typing.py
darl/execution/__init__.py
darl/execution/base.py
darl/execution/dask.py
darl/execution/sequential.py
darl/graph_build/__init__.py
darl/graph_build/base.py
darl/graph_build/dask.py
darl/graph_build/sequential.py
darl-0.0.3.dist-info/licenses/LICENSE
darl-0.0.3.dist-info/METADATA
darl-0.0.3.dist-info/WHEEL
darl-0.0.3.dist-info/top_level.txt
darl-0.0.3.dist-info/RECORD
