Metadata-Version: 2.4
Name: darl
Version: 0.0.3
Summary: Darl is a lightweight code execution framework that transparently provides incremental computations, caching, scenario/shock analysis, parallel/distributed execution and more.
Author-email: Artin Sarraf <asarraf.software@gmail.com>
License: MIT License
Project-URL: Homepage, https://github.com/ArtinSarraf/darl
Requires-Python: >=3.10
License-File: LICENSE
Dynamic: license-file
